unitycatalog/ai/anthropic/__init__.py
unitycatalog/ai/anthropic/toolkit.py
unitycatalog/ai/anthropic/utils.py
unitycatalog/ai/anthropic/version.py
unitycatalog_anthropic-0.2.0.dist-info/METADATA
unitycatalog_anthropic-0.2.0.dist-info/WHEEL
unitycatalog_anthropic-0.2.0.dist-info/RECORD
