Metadata-Version: 2.4
Name: unitycatalog-anthropic
Version: 0.2.0
Summary: Support for Unity Catalog functions as Anthropic tools
Author-email: Ben Wilson <benjamin.wilson@databricks.com>
License: Apache-2.0
Requires-Python: >=3.9
Requires-Dist: anthropic>=0.34.2
Requires-Dist: pydantic<3,>=2
Requires-Dist: unitycatalog-ai
Provides-Extra: databricks
Requires-Dist: unitycatalog-ai[databricks]; extra == 'databricks'
Provides-Extra: databricks-dev
Requires-Dist: unitycatalog-ai[databricks-dev]; extra == 'databricks-dev'
Provides-Extra: dev
Requires-Dist: unitycatalog-ai[dev]; extra == 'dev'
